[{"cmsId":264,"content_en":"Sales Dairy Calender","content_de":"Verkauf Milchkalender","content_eo":"Sales Dairy Calender","content_it":"Calendario di vendita prodotti lattiero-caseari"},{"cmsId":265,"content_en":"Create Sales Event","content_de":"Verkaufsereignis erstellen","content_eo":"Krei Vendokaza\u0135on","content_it":"Crea evento di vendita"},{"cmsId":266,"content_en":"Event Start Time : ","content_de":"Startzeit des Events : ","content_eo":"Eventa Komenca Tempo : ","content_it":"L\u2019evento inizia alle : "},{"cmsId":267,"content_en":"Event End Time : ","content_de":"Endzeit des Events : ","content_eo":"Fina tempo de la evento : ","content_it":"Ora fine diretta : "},{"cmsId":268,"content_en":"Event Title : ","content_de":"Tanzkurs Name : ","content_eo":"Eventa Titolo : ","content_it":"Titolo Evento : "},{"cmsId":269,"content_en":"Please Enter Event Title","content_de":"Bitte geben Sie den Event-Titel ein.","content_eo":"Bonvolu enmeti eventan titolon","content_it":"Inserisci il titolo del tuo evento"},{"cmsId":270,"content_en":"Event Minutes : ","content_de":"Event Ende Minute :","content_eo":"Okaza\u0135aj minutoj :","content_it":"Minuti Fine Evento :"},{"cmsId":271,"content_en":"Save","content_de":"Speichern","content_eo":"Savi","content_it":"Salva"},{"cmsId":272,"content_en":"Delete Event","content_de":"Event l\u00f6schen","content_eo":"Forigi eventon","content_it":"Elimina evento"},{"cmsId":273,"content_en":"Create Follow Up Event","content_de":"Folgeereignis erstellen","content_eo":"Krei sekvantan eventon","content_it":"Crea evento di follow-up"},{"cmsId":274,"content_en":"Previous Event","content_de":"Vorherige Tour","content_eo":"Anta\u016da evento","content_it":"Evento precedente"},{"cmsId":275,"content_en":"Contacts","content_de":"Kontaktadressen","content_eo":"Kontaktaro","content_it":"Contatti"},{"cmsId":276,"content_en":"Search","content_de":"Suche","content_eo":"Ser\u0109u","content_it":"Ricerca"},{"cmsId":277,"content_en":"Customer Search","content_de":"Kundensuche","content_eo":"Klientser\u0109o","content_it":"Ricerca cliente"}]